{
    "background-color": "#0C1A1D",
    "badge-color": "#c2abe0",
    "bold-color": "#c2abe0",
    "comment": "",
    "cursor-background-color": "#0C1A1D",
    "cursor-foreground-color": "#c2abe0",
    "foreground-color": "#c2abe0",
    "highlight-background-color": "#0C1A1D",
    "highlight-foreground-color": "#c2abe0",
    "name": "wal export",
    "palette": [
        "#0C1A1D",
        "#3D445F",
        "#A15367",
        "#2E3893",
        "#5F4EA7",
        "#5347A9",
        "#955EAD",
        "#c2abe0",
        "#87779c",
        "#3D445F",
        "#A15367",
        "#2E3893",
        "#5F4EA7",
        "#5347A9",
        "#955EAD",
        "#c2abe0"
    ],
    "use-badge-color": false,
    "use-bold-color": false,
    "use-cursor-color": false,
    "use-highlight-color": false,
    "use-theme-colors": false
}
